zen_zh/__init__.py
zen_zh/__main__.py
zen_zh/data.py
zen_zh-0.1.0.dist-info/METADATA
zen_zh-0.1.0.dist-info/WHEEL
zen_zh-0.1.0.dist-info/entry_points.txt
zen_zh-0.1.0.dist-info/licenses/LICENSE
zen_zh-0.1.0.dist-info/RECORD
