Metadata-Version: 2.4
Name: zen_zh
Version: 0.1.0
Summary: The Zen of Python 中文版，彩色输出
Project-URL: Homepage, https://github.com/hygroupseries/zen_zh
Project-URL: Repository, https://github.com/hygroupseries/zen_zh
Project-URL: Issues, https://github.com/hygroupseries/zen_zh/issues
Author-email: hygroupseries <gsws_2020@qq.com>
License: CC0 1.0 Universal
License-File: LICENSE
Keywords: aphorisms,chinese,python,translation,zen
Classifier: Operating System :: OS Independent
Classifier: Programming Language :: Python :: 3
Requires-Python: >=3.8
Requires-Dist: colorama>=0.4
